theseus_growth/__init__.py
theseus_growth/aged_DAU_projections.py
theseus_growth/cohort_projections.py
theseus_growth/curve_functions.py
theseus_growth/graphs.py
theseus_growth/retention_profile.py
theseus_growth/theseus_io.py
theseus_growth-0.3.7.dist-info/METADATA
theseus_growth-0.3.7.dist-info/WHEEL
theseus_growth-0.3.7.dist-info/RECORD
