Metadata-Version: 2.1
Name: theseus-growth
Version: 0.3.7
Summary: Theseus is a library of tools to use in marketing analysis
License: MIT
Keywords: cohort analysis,analysis,marketing,media mix model
Author: Eric Benjamin Seufert
Author-email: eric@mobiledevmemo.com
Requires-Python: >=3.9,<4.0
Classifier: License :: OSI Approved :: MIT License
Classifier: Programming Language :: Python :: 3
Classifier: Programming Language :: Python :: 3.9
Classifier: Programming Language :: Python :: 3.10
Classifier: Programming Language :: Python :: 3.11
Requires-Dist: flake8 (>=3.7.9,<4.0.0)
Requires-Dist: matplotlib (>=3.1.2,<4.0.0)
Requires-Dist: numpy (>=1.5.0,<2.0.0)
Requires-Dist: openpyxl (>=3.0.3,<4.0.0)
Requires-Dist: pandas (>=1.5.0,<2.0.0)
Requires-Dist: scipy (>=1.4.1,<2.0.0)
